simple_graph/__init__.py
simple_graph/edges.py
simple_graph/graph.py
simple_graph/vertices.py
tests/__init__.py
tests/test_graph.py
simple_graph-0.2.4.dist-info/LICENSE
simple_graph-0.2.4.dist-info/METADATA
simple_graph-0.2.4.dist-info/WHEEL
simple_graph-0.2.4.dist-info/top_level.txt
simple_graph-0.2.4.dist-info/RECORD
