Metadata-Version: 2.1
Name: simple-graph
Version: 0.2.4
Summary: A simple graph package
Home-page: https://github.com/jiayingwang/simple_graph
Author: Jiaying Wang
Author-email: jiaying@sjzu.edu.cn
License: UNKNOWN
Platform: UNKNOWN
Classifier: Programming Language :: Python :: 3
Classifier: License :: OSI Approved :: MIT License
Classifier: Operating System :: OS Independent
Requires-Python: >=3.6
